simple_interpolation/__init__.py
simple_interpolation/_nbdev.py
simple_interpolation/core.py
simple_interpolation/prophet_sensibility.py
simple_interpolation/simple_interpolation.py
simple_interpolation-0.1.15.dist-info/LICENSE
simple_interpolation-0.1.15.dist-info/METADATA
simple_interpolation-0.1.15.dist-info/WHEEL
simple_interpolation-0.1.15.dist-info/entry_points.txt
simple_interpolation-0.1.15.dist-info/top_level.txt
simple_interpolation-0.1.15.dist-info/RECORD
