Metadata-Version: 2.1
Name: simple-interpolation
Version: 0.1.15
Summary: Brownian Bridge interpolation of timeseries, built to use with Pandas.
Home-page: https://github.com/pnmartinez/simple_interpolation/tree/master/
Author: Pablo Navarro
Author-email: navarro@cresmartadvisor.com
License: Apache Software License 2.0
Keywords: interpolation,Pandas,timeseries,brownian bridge,Wiener process
Platform: UNKNOWN
Classifier: Development Status :: 3 - Alpha
Classifier: Intended Audience :: Developers
Classifier: License :: OSI Approved :: Apache Software License
Classifier: Natural Language :: English
Classifier: Programming Language :: Python :: 3.6
Classifier: Programming Language :: Python :: 3.7
Classifier: Programming Language :: Python :: 3.8
Requires-Python: >=3.6
Requires-Dist: numpy
Requires-Dist: pandas
Requires-Dist: matplotlib
